minimal_log_host/__init__.py
minimal_log_host/admin.py
minimal_log_host/models.py
minimal_log_host/urls.py
minimal_log_host/utils.py
minimal_log_host/views.py
minimal_log_host/migrations/0001_initial.py
minimal_log_host/migrations/0002_on_delete.py
minimal_log_host/migrations/__init__.py
minimal_log_host/templates/minimal_log/add_entry.html
minimal_log_host/templates/minimal_log/confirm_resolve.html
minimal_log_host/templates/minimal_log/list.html
minimal_log_host/templates/minimal_log/permission_denied.html
minimal_logger/__init__.py
minimal_logger/context.py
minimal_logger/django_logger.py
minimal_logger/js_handler.html
minimal_logger/python_log.py
minimal_logger/urls.py
minimal_logger/views_javascript.py
django_minimal_log-0.7.2.dist-info/LICENSE.txt
django_minimal_log-0.7.2.dist-info/METADATA
django_minimal_log-0.7.2.dist-info/WHEEL
django_minimal_log-0.7.2.dist-info/top_level.txt
django_minimal_log-0.7.2.dist-info/RECORD
