Metadata-Version: 2.1
Name: django-minimal-log
Version: 0.7.2
Summary: Simple logging functionality for Django
Home-page: https://github.com/mverleg/django_minimal_log
Author: Mark V
Author-email: mdilligaf@gmail.com
Maintainer: (the author)
License: LICENSE.txt
Keywords: django,logging
Platform: UNKNOWN
Classifier: Development Status :: 5 - Production/Stable
Classifier: Intended Audience :: Developers
Classifier: Natural Language :: English
Classifier: License :: OSI Approved :: BSD License
Classifier: Operating System :: OS Independent
Classifier: Topic :: System :: Logging
Classifier: Topic :: System :: Monitoring
Classifier: Programming Language :: Python
Classifier: Programming Language :: Python :: 2
Classifier: Programming Language :: Python :: 2.6
Classifier: Programming Language :: Python :: 2.7
Classifier: Programming Language :: Python :: 3
Classifier: Programming Language :: Python :: 3.3
Classifier: Programming Language :: Python :: 3.4
Classifier: Programming Language :: Python :: 3.5
Classifier: Programming Language :: Python :: Implementation :: PyPy
Classifier: Topic :: Software Development :: Libraries :: Python Modules
Requires-Dist: django
Requires-Dist: requests
Requires-Dist: django-ipware (==2.*)
